{
	"ar": {
		"accept": "",
		"addRule": "",
		"am": "",
		"apply": "",
		"aria": {
			"cancelEdit": "",
			"close": "",
			"collapseLabel": "",
			"collapseRow": "",
			"editRow": "",
			"expandLabel": "",
			"expandRow": "",
			"falseLabel": "",
			"filterConstraint": "",
			"filterOperator": "",
			"firstPageLabel": "",
			"gridView": "",
			"hideFilterMenu": "",
			"jumpToPageDropdownLabel": "",
			"jumpToPageInputLabel": "",
			"lastPageLabel": "",
			"listLabel": "",
			"listView": "",
			"maximizeLabel": "",
			"minimizeLabel": "",
			"moveAllToSource": "",
			"moveAllToTarget": "",
			"moveBottom": "",
			"moveDown": "",
			"moveTop": "",
			"moveToSource": "",
			"moveToTarget": "",
			"moveUp": "",
			"navigation": "",
			"next": "",
			"nextPageLabel": "",
			"nullLabel": "",
			"otpLabel": "",
			"pageLabel": "",
			"passwordHide": "",
			"passwordShow": "",
			"previous": "",
			"prevPageLabel": "",
			"removeLabel": "",
			"rotateLeft": "",
			"rotateRight": "",
			"rowsPerPageLabel": "",
			"saveEdit": "",
			"scrollTop": "",
			"selectAll": "",
			"selectColor": "",
			"selectLabel": "",
			"selectRow": "",
			"showFilterMenu": "",
			"slide": "",
			"slideNumber": "",
			"star": "",
			"stars": "",
			"trueLabel": "",
			"unselectAll": "",
			"unselectLabel": "",
			"unselectRow": "",
			"zoomImage": "",
			"zoomIn": "",
			"zoomOut": ""
		},
		"cancel": "",
		"choose": "",
		"chooseDate": "",
		"chooseMonth": "",
		"chooseYear": "",
		"clear": "",
		"completed": "",
		"contains": "",
		"custom": "",
		"dateAfter": "",
		"dateBefore": "",
		"dateFormat": "",
		"dateIs": "",
		"dateIsNot": "",
		"dayNames": [
			"",
			"",
			"",
			"",
			"",
			"",
			""
		],
		"dayNamesMin": [
			"",
			"",
			"",
			"",
			"",
			"",
			""
		],
		"dayNamesShort": [
			"",
			"",
			"",
			"",
			"",
			"",
			""
		],
		"emptyFilterMessage": "",
		"emptyMessage": "",
		"emptySearchMessage": "",
		"emptySelectionMessage": "",
		"endsWith": "",
		"equals": "",
		"fileChosenMessage": "",
		"fileSizeTypes": [
			"",
			"",
			"",
			"",
			"",
			"",
			"",
			"",
			""
		],
		"filter": "",
		"gt": "",
		"gte": "",
		"lt": "",
		"lte": "",
		"matchAll": "",
		"matchAny": "",
		"medium": "",
		"monthNames": [
			"",
			"",
			"",
			"",
			"",
			"",
			"",
			"",
			"",
			"",
			"",
			""
		],
		"monthNamesShort": [
			"",
			"",
			"",
			"",
			"",
			"",
			"",
			"",
			"",
			"",
			"",
			""
		],
		"nextDecade": "",
		"nextHour": "",
		"nextMinute": "",
		"nextMonth": "",
		"nextSecond": "",
		"nextYear": "",
		"noFileChosenMessage": "",
		"noFilter": "",
		"notContains": "",
		"notEquals": "",
		"now": "",
		"passwordPrompt": "",
		"pending": "",
		"pm": "",
		"prevDecade": "",
		"prevHour": "",
		"prevMinute": "",
		"prevMonth": "",
		"prevSecond": "",
		"prevYear": "",
		"reject": "",
		"removeRule": "",
		"searchMessage": "",
		"selectionMessage": "",
		"startsWith": "",
		"strong": "",
		"today": "",
		"upload": "",
		"weak": "",
		"weekHeader": ""
	},
	"ar-TN": {
		"accept": "",
		"addRule": "",
		"am": "",
		"apply": "",
		"aria": {
			"cancelEdit": "",
			"close": "",
			"collapseLabel": "",
			"collapseRow": "",
			"editRow": "",
			"expandLabel": "",
			"expandRow": "",
			"falseLabel": "",
			"filterConstraint": "",
			"filterOperator": "",
			"firstPageLabel": "",
			"gridView": "",
			"hideFilterMenu": "",
			"jumpToPageDropdownLabel": "",
			"jumpToPageInputLabel": "",
			"lastPageLabel": "",
			"listLabel": "",
			"listView": "",
			"maximizeLabel": "",
			"minimizeLabel": "",
			"moveAllToSource": "",
			"moveAllToTarget": "",
			"moveBottom": "",
			"moveDown": "",
			"moveTop": "",
			"moveToSource": "",
			"moveToTarget": "",
			"moveUp": "",
			"navigation": "",
			"next": "",
			"nextPageLabel": "",
			"nullLabel": "",
			"otpLabel": "",
			"pageLabel": "",
			"passwordHide": "",
			"passwordShow": "",
			"previous": "",
			"prevPageLabel": "",
			"removeLabel": "",
			"rotateLeft": "",
			"rotateRight": "",
			"rowsPerPageLabel": "",
			"saveEdit": "",
			"scrollTop": "",
			"selectAll": "",
			"selectColor": "",
			"selectLabel": "",
			"selectRow": "",
			"showFilterMenu": "",
			"slide": "",
			"slideNumber": "",
			"star": "",
			"stars": "",
			"trueLabel": "",
			"unselectAll": "",
			"unselectLabel": "",
			"unselectRow": "",
			"zoomImage": "",
			"zoomIn": "",
			"zoomOut": ""
		},
		"cancel": "",
		"choose": "",
		"chooseDate": "",
		"chooseMonth": "",
		"chooseYear": "",
		"clear": "",
		"completed": "",
		"contains": "",
		"custom": "",
		"dateAfter": "",
		"dateBefore": "",
		"dateFormat": "",
		"dateIs": "",
		"dateIsNot": "",
		"dayNames": [
			"",
			"",
			"",
			"",
			"",
			"",
			""
		],
		"dayNamesMin": [
			"",
			"",
			"",
			"",
			"",
			"",
			""
		],
		"dayNamesShort": [
			"",
			"",
			"",
			"",
			"",
			"",
			""
		],
		"emptyFilterMessage": "",
		"emptyMessage": "",
		"emptySearchMessage": "",
		"emptySelectionMessage": "",
		"endsWith": "",
		"equals": "",
		"fileChosenMessage": "",
		"fileSizeTypes": [
			"",
			"",
			"",
			"",
			"",
			"",
			"",
			"",
			""
		],
		"filter": "",
		"gt": "",
		"gte": "",
		"lt": "",
		"lte": "",
		"matchAll": "",
		"matchAny": "",
		"medium": "",
		"monthNames": [
			"",
			"",
			"",
			"",
			"",
			"",
			"",
			"",
			"",
			"",
			"",
			""
		],
		"monthNamesShort": [
			"",
			"",
			"",
			"",
			"",
			"",
			"",
			"",
			"",
			"",
			"",
			""
		],
		"nextDecade": "",
		"nextHour": "",
		"nextMinute": "",
		"nextMonth": "",
		"nextSecond": "",
		"nextYear": "",
		"noFileChosenMessage": "",
		"noFilter": "",
		"notContains": "",
		"notEquals": "",
		"now": "",
		"passwordPrompt": "",
		"pending": "",
		"pm": "",
		"prevDecade": "",
		"prevHour": "",
		"prevMinute": "",
		"prevMonth": "",
		"prevSecond": "",
		"prevYear": "",
		"reject": "",
		"removeRule": "",
		"searchMessage": "",
		"selectionMessage": "",
		"startsWith": "",
		"strong": "",
		"today": "",
		"upload": "",
		"weak": "",
		"weekHeader": ""
	},
	"bg": {
		"accept": "",
		"addRule": "",
		"am": "",
		"apply": "",
		"aria": {
			"cancelEdit": "",
			"close": "",
			"collapseLabel": "",
			"collapseRow": "",
			"editRow": "",
			"expandLabel": "",
			"expandRow": "",
			"falseLabel": "",
			"filterConstraint": "",
			"filterOperator": "",
			"firstPageLabel": "",
			"gridView": "",
			"hideFilterMenu": "",
			"jumpToPageDropdownLabel": "",
			"jumpToPageInputLabel": "",
			"lastPageLabel": "",
			"listLabel": "",
			"listView": "",
			"maximizeLabel": "",
			"minimizeLabel": "",
			"moveAllToSource": "",
			"moveAllToTarget": "",
			"moveBottom": "",
			"moveDown": "",
			"moveTop": "",
			"moveToSource": "",
			"moveToTarget": "",
			"moveUp": "",
			"navigation": "",
			"next": "",
			"nextPageLabel": "",
			"nullLabel": "",
			"otpLabel": "",
			"pageLabel": "",
			"passwordHide": "",
			"passwordShow": "",
			"previous": "",
			"prevPageLabel": "",
			"removeLabel": "",
			"rotateLeft": "",
			"rotateRight": "",
			"rowsPerPageLabel": "",
			"saveEdit": "",
			"scrollTop": "",
			"selectAll": "",
			"selectColor": "",
			"selectLabel": "",
			"selectRow": "",
			"showFilterMenu": "",
			"slide": "",
			"slideNumber": "",
			"star": "",
			"stars": "",
			"trueLabel": "",
			"unselectAll": "",
			"unselectLabel": "",
			"unselectRow": "",
			"zoomImage": "",
			"zoomIn": "",
			"zoomOut": ""
		},
		"cancel": "",
		"choose": "",
		"chooseDate": "",
		"chooseMonth": "",
		"chooseYear": "",
		"clear": "",
		"completed": "",
		"contains": "",
		"custom": "",
		"dateAfter": "",
		"dateBefore": "",
		"dateFormat": "",
		"dateIs": "",
		"dateIsNot": "",
		"dayNames": [
			"",
			"",
			"",
			"",
			"",
			"",
			""
		],
		"dayNamesMin": [
			"",
			"",
			"",
			"",
			"",
			"",
			""
		],
		"dayNamesShort": [
			"",
			"",
			"",
			"",
			"",
			"",
			""
		],
		"emptyFilterMessage": "",
		"emptyMessage": "",
		"emptySearchMessage": "",
		"emptySelectionMessage": "",
		"endsWith": "",
		"equals": "",
		"fileChosenMessage": "",
		"fileSizeTypes": [
			"",
			"",
			"",
			"",
			"",
			"",
			"",
			"",
			""
		],
		"filter": "",
		"gt": "",
		"gte": "",
		"lt": "",
		"lte": "",
		"matchAll": "",
		"matchAny": "",
		"medium": "",
		"monthNames": [
			"",
			"",
			"",
			"",
			"",
			"",
			"",
			"",
			"",
			"",
			"",
			""
		],
		"monthNamesShort": [
			"",
			"",
			"",
			"",
			"",
			"",
			"",
			"",
			"",
			"",
			"",
			""
		],
		"nextDecade": "",
		"nextHour": "",
		"nextMinute": "",
		"nextMonth": "",
		"nextSecond": "",
		"nextYear": "",
		"noFileChosenMessage": "",
		"noFilter": "",
		"notContains": "",
		"notEquals": "",
		"now": "",
		"passwordPrompt": "",
		"pending": "",
		"pm": "",
		"prevDecade": "",
		"prevHour": "",
		"prevMinute": "",
		"prevMonth": "",
		"prevSecond": "",
		"prevYear": "",
		"reject": "",
		"removeRule": "",
		"searchMessage": "",
		"selectionMessage": "",
		"startsWith": "",
		"strong": "",
		"today": "",
		"upload": "",
		"weak": "",
		"weekHeader": ""
	},
	"bn": {
		"accept": "",
		"addRule": "",
		"am": "",
		"apply": "",
		"aria": {
			"cancelEdit": "",
			"close": "",
			"collapseLabel": "",
			"collapseRow": "",
			"editRow": "",
			"expandLabel": "",
			"expandRow": "",
			"falseLabel": "",
			"filterConstraint": "",
			"filterOperator": "",
			"firstPageLabel": "",
			"gridView": "",
			"hideFilterMenu": "",
			"jumpToPageDropdownLabel": "",
			"jumpToPageInputLabel": "",
			"lastPageLabel": "",
			"listLabel": "",
			"listView": "",
			"maximizeLabel": "",
			"minimizeLabel": "",
			"moveAllToSource": "",
			"moveAllToTarget": "",
			"moveBottom": "",
			"moveDown": "",
			"moveTop": "",
			"moveToSource": "",
			"moveToTarget": "",
			"moveUp": "",
			"navigation": "",
			"next": "",
			"nextPageLabel": "",
			"nullLabel": "",
			"otpLabel": "",
			"pageLabel": "",
			"passwordHide": "",
			"passwordShow": "",
			"previous": "",
			"prevPageLabel": "",
			"removeLabel": "",
			"rotateLeft": "",
			"rotateRight": "",
			"rowsPerPageLabel": "",
			"saveEdit": "",
			"scrollTop": "",
			"selectAll": "",
			"selectColor": "",
			"selectLabel": "",
			"selectRow": "",
			"showFilterMenu": "",
			"slide": "",
			"slideNumber": "",
			"star": "",
			"stars": "",
			"trueLabel": "",
			"unselectAll": "",
			"unselectLabel": "",
			"unselectRow": "",
			"zoomImage": "",
			"zoomIn": "",
			"zoomOut": ""
		},
		"cancel": "",
		"choose": "",
		"chooseDate": "",
		"chooseMonth": "",
		"chooseYear": "",
		"clear": "",
		"completed": "",
		"contains": "",
		"custom": "",
		"dateAfter": "",
		"dateBefore": "",
		"dateFormat": "",
		"dateIs": "",
		"dateIsNot": "",
		"dayNames": [
			"",
			"",
			"",
			"",
			"",
			"",
			""
		],
		"dayNamesMin": [
			"",
			"",
			"",
			"",
			"",
			"",
			""
		],
		"dayNamesShort": [
			"",
			"",
			"",
			"",
			"",
			"",
			""
		],
		"emptyFilterMessage": "",
		"emptyMessage": "",
		"emptySearchMessage": "",
		"emptySelectionMessage": "",
		"endsWith": "",
		"equals": "",
		"fileChosenMessage": "",
		"fileSizeTypes": [
			"",
			"",
			"",
			"",
			"",
			"",
			"",
			"",
			""
		],
		"filter": "",
		"gt": "",
		"gte": "",
		"lt": "",
		"lte": "",
		"matchAll": "",
		"matchAny": "",
		"medium": "",
		"monthNames": [
			"",
			"",
			"",
			"",
			"",
			"",
			"",
			"",
			"",
			"",
			"",
			""
		],
		"monthNamesShort": [
			"",
			"",
			"",
			"",
			"",
			"",
			"",
			"",
			"",
			"",
			"",
			""
		],
		"nextDecade": "",
		"nextHour": "",
		"nextMinute": "",
		"nextMonth": "",
		"nextSecond": "",
		"nextYear": "",
		"noFileChosenMessage": "",
		"noFilter": "",
		"notContains": "",
		"notEquals": "",
		"now": "",
		"passwordPrompt": "",
		"pending": "",
		"pm": "",
		"prevDecade": "",
		"prevHour": "",
		"prevMinute": "",
		"prevMonth": "",
		"prevSecond": "",
		"prevYear": "",
		"reject": "",
		"removeRule": "",
		"searchMessage": "",
		"selectionMessage": "",
		"startsWith": "",
		"strong": "",
		"today": "",
		"upload": "",
		"weak": "",
		"weekHeader": ""
	},
	"bs": {
		"accept": "",
		"addRule": "",
		"am": "",
		"apply": "",
		"aria": {
			"cancelEdit": "",
			"close": "",
			"collapseLabel": "",
			"collapseRow": "",
			"editRow": "",
			"expandLabel": "",
			"expandRow": "",
			"falseLabel": "",
			"filterConstraint": "",
			"filterOperator": "",
			"firstPageLabel": "",
			"gridView": "",
			"hideFilterMenu": "",
			"jumpToPageDropdownLabel": "",
			"jumpToPageInputLabel": "",
			"lastPageLabel": "",
			"listLabel": "",
			"listView": "",
			"maximizeLabel": "",
			"minimizeLabel": "",
			"moveAllToSource": "",
			"moveAllToTarget": "",
			"moveBottom": "",
			"moveDown": "",
			"moveTop": "",
			"moveToSource": "",
			"moveToTarget": "",
			"moveUp": "",
			"navigation": "",
			"next": "",
			"nextPageLabel": "",
			"nullLabel": "",
			"otpLabel": "",
			"pageLabel": "",
			"passwordHide": "",
			"passwordShow": "",
			"previous": "",
			"prevPageLabel": "",
			"removeLabel": "",
			"rotateLeft": "",
			"rotateRight": "",
			"rowsPerPageLabel": "",
			"saveEdit": "",
			"scrollTop": "",
			"selectAll": "",
			"selectColor": "",
			"selectLabel": "",
			"selectRow": "",
			"showFilterMenu": "",
			"slide": "",
			"slideNumber": "",
			"star": "",
			"stars": "",
			"trueLabel": "",
			"unselectAll": "",
			"unselectLabel": "",
			"unselectRow": "",
			"zoomImage": "",
			"zoomIn": "",
			"zoomOut": ""
		},
		"cancel": "",
		"choose": "",
		"chooseDate": "",
		"chooseMonth": "",
		"chooseYear": "",
		"clear": "",
		"completed": "",
		"contains": "",
		"custom": "",
		"dateAfter": "",
		"dateBefore": "",
		"dateFormat": "",
		"dateIs": "",
		"dateIsNot": "",
		"dayNames": [
			"",
			"",
			"",
			"",
			"",
			"",
			""
		],
		"dayNamesMin": [
			"",
			"",
			"",
			"",
			"",
			"",
			""
		],
		"dayNamesShort": [
			"",
			"",
			"",
			"",
			"",
			"",
			""
		],
		"emptyFilterMessage": "",
		"emptyMessage": "",
		"emptySearchMessage": "",
		"emptySelectionMessage": "",
		"endsWith": "",
		"equals": "",
		"fileChosenMessage": "",
		"fileSizeTypes": [
			"",
			"",
			"",
			"",
			"",
			"",
			"",
			"",
			""
		],
		"filter": "",
		"gt": "",
		"gte": "",
		"lt": "",
		"lte": "",
		"matchAll": "",
		"matchAny": "",
		"medium": "",
		"monthNames": [
			"",
			"",
			"",
			"",
			"",
			"",
			"",
			"",
			"",
			"",
			"",
			""
		],
		"monthNamesShort": [
			"",
			"",
			"",
			"",
			"",
			"",
			"",
			"",
			"",
			"",
			"",
			""
		],
		"nextDecade": "",
		"nextHour": "",
		"nextMinute": "",
		"nextMonth": "",
		"nextSecond": "",
		"nextYear": "",
		"noFileChosenMessage": "",
		"noFilter": "",
		"notContains": "",
		"notEquals": "",
		"now": "",
		"passwordPrompt": "",
		"pending": "",
		"pm": "",
		"prevDecade": "",
		"prevHour": "",
		"prevMinute": "",
		"prevMonth": "",
		"prevSecond": "",
		"prevYear": "",
		"reject": "",
		"removeRule": "",
		"searchMessage": "",
		"selectionMessage": "",
		"startsWith": "",
		"strong": "",
		"today": "",
		"upload": "",
		"weak": "",
		"weekHeader": ""
	},
	"ca": {
		"accept": "",
		"addRule": "",
		"am": "",
		"apply": "",
		"aria": {
			"cancelEdit": "",
			"close": "",
			"collapseLabel": "",
			"collapseRow": "",
			"editRow": "",
			"expandLabel": "",
			"expandRow": "",
			"falseLabel": "",
			"filterConstraint": "",
			"filterOperator": "",
			"firstPageLabel": "",
			"gridView": "",
			"hideFilterMenu": "",
			"jumpToPageDropdownLabel": "",
			"jumpToPageInputLabel": "",
			"lastPageLabel": "",
			"listLabel": "",
			"listView": "",
			"maximizeLabel": "",
			"minimizeLabel": "",
			"moveAllToSource": "",
			"moveAllToTarget": "",
			"moveBottom": "",
			"moveDown": "",
			"moveTop": "",
			"moveToSource": "",
			"moveToTarget": "",
			"moveUp": "",
			"navigation": "",
			"next": "",
			"nextPageLabel": "",
			"nullLabel": "",
			"otpLabel": "",
			"pageLabel": "",
			"passwordHide": "",
			"passwordShow": "",
			"previous": "",
			"prevPageLabel": "",
			"removeLabel": "",
			"rotateLeft": "",
			"rotateRight": "",
			"rowsPerPageLabel": "",
			"saveEdit": "",
			"scrollTop": "",
			"selectAll": "",
			"selectColor": "",
			"selectLabel": "",
			"selectRow": "",
			"showFilterMenu": "",
			"slide": "",
			"slideNumber": "",
			"star": "",
			"stars": "",
			"trueLabel": "",
			"unselectAll": "",
			"unselectLabel": "",
			"unselectRow": "",
			"zoomImage": "",
			"zoomIn": "",
			"zoomOut": ""
		},
		"cancel": "",
		"choose": "",
		"chooseDate": "",
		"chooseMonth": "",
		"chooseYear": "",
		"clear": "",
		"completed": "",
		"contains": "",
		"custom": "",
		"dateAfter": "",
		"dateBefore": "",
		"dateFormat": "",
		"dateIs": "",
		"dateIsNot": "",
		"dayNames": [
			"",
			"",
			"",
			"",
			"",
			"",
			""
		],
		"dayNamesMin": [
			"",
			"",
			"",
			"",
			"",
			"",
			""
		],
		"dayNamesShort": [
			"",
			"",
			"",
			"",
			"",
			"",
			""
		],
		"emptyFilterMessage": "",
		"emptyMessage": "",
		"emptySearchMessage": "",
		"emptySelectionMessage": "",
		"endsWith": "",
		"equals": "",
		"fileChosenMessage": "",
		"fileSizeTypes": [
			"",
			"",
			"",
			"",
			"",
			"",
			"",
			"",
			""
		],
		"filter": "",
		"gt": "",
		"gte": "",
		"lt": "",
		"lte": "",
		"matchAll": "",
		"matchAny": "",
		"medium": "",
		"monthNames": [
			"",
			"",
			"",
			"",
			"",
			"",
			"",
			"",
			"",
			"",
			"",
			""
		],
		"monthNamesShort": [
			"",
			"",
			"",
			"",
			"",
			"",
			"",
			"",
			"",
			"",
			"",
			""
		],
		"nextDecade": "",
		"nextHour": "",
		"nextMinute": "",
		"nextMonth": "",
		"nextSecond": "",
		"nextYear": "",
		"noFileChosenMessage": "",
		"noFilter": "",
		"notContains": "",
		"notEquals": "",
		"now": "",
		"passwordPrompt": "",
		"pending": "",
		"pm": "",
		"prevDecade": "",
		"prevHour": "",
		"prevMinute": "",
		"prevMonth": "",
		"prevSecond": "",
		"prevYear": "",
		"reject": "",
		"removeRule": "",
		"searchMessage": "",
		"selectionMessage": "",
		"startsWith": "",
		"strong": "",
		"today": "",
		"upload": "",
		"weak": "",
		"weekHeader": ""
	},
	"cs": {
		"accept": "",
		"addRule": "",
		"am": "",
		"apply": "",
		"aria": {
			"cancelEdit": "",
			"close": "",
			"collapseLabel": "",
			"collapseRow": "",
			"editRow": "",
			"expandLabel": "",
			"expandRow": "",
			"falseLabel": "",
			"filterConstraint": "",
			"filterOperator": "",
			"firstPageLabel": "",
			"gridView": "",
			"hideFilterMenu": "",
			"jumpToPageDropdownLabel": "",
			"jumpToPageInputLabel": "",
			"lastPageLabel": "",
			"listLabel": "",
			"listView": "",
			"maximizeLabel": "",
			"minimizeLabel": "",
			"moveAllToSource": "",
			"moveAllToTarget": "",
			"moveBottom": "",
			"moveDown": "",
			"moveTop": "",
			"moveToSource": "",
			"moveToTarget": "",
			"moveUp": "",
			"navigation": "",
			"next": "",
			"nextPageLabel": "",
			"nullLabel": "",
			"otpLabel": "",
			"pageLabel": "",
			"passwordHide": "",
			"passwordShow": "",
			"previous": "",
			"prevPageLabel": "",
			"removeLabel": "",
			"rotateLeft": "",
			"rotateRight": "",
			"rowsPerPageLabel": "",
			"saveEdit": "",
			"scrollTop": "",
			"selectAll": "",
			"selectColor": "",
			"selectLabel": "",
			"selectRow": "",
			"showFilterMenu": "",
			"slide": "",
			"slideNumber": "",
			"star": "",
			"stars": "",
			"trueLabel": "",
			"unselectAll": "",
			"unselectLabel": "",
			"unselectRow": "",
			"zoomImage": "",
			"zoomIn": "",
			"zoomOut": ""
		},
		"cancel": "",
		"choose": "",
		"chooseDate": "",
		"chooseMonth": "",
		"chooseYear": "",
		"clear": "",
		"completed": "",
		"contains": "",
		"custom": "",
		"dateAfter": "",
		"dateBefore": "",
		"dateFormat": "",
		"dateIs": "",
		"dateIsNot": "",
		"dayNames": [
			"",
			"",
			"",
			"",
			"",
			"",
			""
		],
		"dayNamesMin": [
			"",
			"",
			"",
			"",
			"",
			"",
			""
		],
		"dayNamesShort": [
			"",
			"",
			"",
			"",
			"",
			"",
			""
		],
		"emptyFilterMessage": "",
		"emptyMessage": "",
		"emptySearchMessage": "",
		"emptySelectionMessage": "",
		"endsWith": "",
		"equals": "",
		"fileChosenMessage": "",
		"fileSizeTypes": [
			"",
			"",
			"",
			"",
			"",
			"",
			"",
			"",
			""
		],
		"filter": "",
		"gt": "",
		"gte": "",
		"lt": "",
		"lte": "",
		"matchAll": "",
		"matchAny": "",
		"medium": "",
		"monthNames": [
			"",
			"",
			"",
			"",
			"",
			"",
			"",
			"",
			"",
			"",
			"",
			""
		],
		"monthNamesShort": [
			"",
			"",
			"",
			"",
			"",
			"",
			"",
			"",
			"",
			"",
			"",
			""
		],
		"nextDecade": "",
		"nextHour": "",
		"nextMinute": "",
		"nextMonth": "",
		"nextSecond": "",
		"nextYear": "",
		"noFileChosenMessage": "",
		"noFilter": "",
		"notContains": "",
		"notEquals": "",
		"now": "",
		"passwordPrompt": "",
		"pending": "",
		"pm": "",
		"prevDecade": "",
		"prevHour": "",
		"prevMinute": "",
		"prevMonth": "",
		"prevSecond": "",
		"prevYear": "",
		"reject": "",
		"removeRule": "",
		"searchMessage": "",
		"selectionMessage": "",
		"startsWith": "",
		"strong": "",
		"today": "",
		"upload": "",
		"weak": "",
		"weekHeader": ""
	},
	"da": {
		"accept": "",
		"addRule": "",
		"am": "",
		"apply": "",
		"aria": {
			"cancelEdit": "",
			"close": "",
			"collapseLabel": "",
			"collapseRow": "",
			"editRow": "",
			"expandLabel": "",
			"expandRow": "",
			"falseLabel": "",
			"filterConstraint": "",
			"filterOperator": "",
			"firstPageLabel": "",
			"gridView": "",
			"hideFilterMenu": "",
			"jumpToPageDropdownLabel": "",
			"jumpToPageInputLabel": "",
			"lastPageLabel": "",
			"listLabel": "",
			"listView": "",
			"maximizeLabel": "",
			"minimizeLabel": "",
			"moveAllToSource": "",
			"moveAllToTarget": "",
			"moveBottom": "",
			"moveDown": "",
			"moveTop": "",
			"moveToSource": "",
			"moveToTarget": "",
			"moveUp": "",
			"navigation": "",
			"next": "",
			"nextPageLabel": "",
			"nullLabel": "",
			"otpLabel": "",
			"pageLabel": "",
			"passwordHide": "",
			"passwordShow": "",
			"previous": "",
			"prevPageLabel": "",
			"removeLabel": "",
			"rotateLeft": "",
			"rotateRight": "",
			"rowsPerPageLabel": "",
			"saveEdit": "",
			"scrollTop": "",
			"selectAll": "",
			"selectColor": "",
			"selectLabel": "",
			"selectRow": "",
			"showFilterMenu": "",
			"slide": "",
			"slideNumber": "",
			"star": "",
			"stars": "",
			"trueLabel": "",
			"unselectAll": "",
			"unselectLabel": "",
			"unselectRow": "",
			"zoomImage": "",
			"zoomIn": "",
			"zoomOut": ""
		},
		"cancel": "",
		"choose": "",
		"chooseDate": "",
		"chooseMonth": "",
		"chooseYear": "",
		"clear": "",
		"completed": "",
		"contains": "",
		"custom": "",
		"dateAfter": "",
		"dateBefore": "",
		"dateFormat": "",
		"dateIs": "",
		"dateIsNot": "",
		"dayNames": [
			"",
			"",
			"",
			"",
			"",
			"",
			""
		],
		"dayNamesMin": [
			"",
			"",
			"",
			"",
			"",
			"",
			""
		],
		"dayNamesShort": [
			"",
			"",
			"",
			"",
			"",
			"",
			""
		],
		"emptyFilterMessage": "",
		"emptyMessage": "",
		"emptySearchMessage": "",
		"emptySelectionMessage": "",
		"endsWith": "",
		"equals": "",
		"fileChosenMessage": "",
		"fileSizeTypes": [
			"",
			"",
			"",
			"",
			"",
			"",
			"",
			"",
			""
		],
		"filter": "",
		"gt": "",
		"gte": "",
		"lt": "",
		"lte": "",
		"matchAll": "",
		"matchAny": "",
		"medium": "",
		"monthNames": [
			"",
			"",
			"",
			"",
			"",
			"",
			"",
			"",
			"",
			"",
			"",
			""
		],
		"monthNamesShort": [
			"",
			"",
			"",
			"",
			"",
			"",
			"",
			"",
			"",
			"",
			"",
			""
		],
		"nextDecade": "",
		"nextHour": "",
		"nextMinute": "",
		"nextMonth": "",
		"nextSecond": "",
		"nextYear": "",
		"noFileChosenMessage": "",
		"noFilter": "",
		"notContains": "",
		"notEquals": "",
		"now": "",
		"passwordPrompt": "",
		"pending": "",
		"pm": "",
		"prevDecade": "",
		"prevHour": "",
		"prevMinute": "",
		"prevMonth": "",
		"prevSecond": "",
		"prevYear": "",
		"reject": "",
		"removeRule": "",
		"searchMessage": "",
		"selectionMessage": "",
		"startsWith": "",
		"strong": "",
		"today": "",
		"upload": "",
		"weak": "",
		"weekHeader": ""
	},
	"de": {
		"accept": "",
		"addRule": "",
		"am": "",
		"apply": "",
		"aria": {
			"cancelEdit": "",
			"close": "",
			"collapseLabel": "",
			"collapseRow": "",
			"editRow": "",
			"expandLabel": "",
			"expandRow": "",
			"falseLabel": "",
			"filterConstraint": "",
			"filterOperator": "",
			"firstPageLabel": "",
			"gridView": "",
			"hideFilterMenu": "",
			"jumpToPageDropdownLabel": "",
			"jumpToPageInputLabel": "",
			"lastPageLabel": "",
			"listLabel": "",
			"listView": "",
			"maximizeLabel": "",
			"minimizeLabel": "",
			"moveAllToSource": "",
			"moveAllToTarget": "",
			"moveBottom": "",
			"moveDown": "",
			"moveTop": "",
			"moveToSource": "",
			"moveToTarget": "",
			"moveUp": "",
			"navigation": "",
			"next": "",
			"nextPageLabel": "",
			"nullLabel": "",
			"otpLabel": "",
			"pageLabel": "",
			"passwordHide": "",
			"passwordShow": "",
			"previous": "",
			"prevPageLabel": "",
			"removeLabel": "",
			"rotateLeft": "",
			"rotateRight": "",
			"rowsPerPageLabel": "",
			"saveEdit": "",
			"scrollTop": "",
			"selectAll": "",
			"selectColor": "",
			"selectLabel": "",
			"selectRow": "",
			"showFilterMenu": "",
			"slide": "",
			"slideNumber": "",
			"star": "",
			"stars": "",
			"trueLabel": "",
			"unselectAll": "",
			"unselectLabel": "",
			"unselectRow": "",
			"zoomImage": "",
			"zoomIn": "",
			"zoomOut": ""
		},
		"cancel": "",
		"choose": "",
		"chooseDate": "",
		"chooseMonth": "",
		"chooseYear": "",
		"clear": "",
		"completed": "",
		"contains": "",
		"custom": "",
		"dateAfter": "",
		"dateBefore": "",
		"dateFormat": "",
		"dateIs": "",
		"dateIsNot": "",
		"dayNames": [
			"",
			"",
			"",
			"",
			"",
			"",
			""
		],
		"dayNamesMin": [
			"",
			"",
			"",
			"",
			"",
			"",
			""
		],
		"dayNamesShort": [
			"",
			"",
			"",
			"",
			"",
			"",
			""
		],
		"emptyFilterMessage": "",
		"emptyMessage": "",
		"emptySearchMessage": "",
		"emptySelectionMessage": "",
		"endsWith": "",
		"equals": "",
		"fileChosenMessage": "",
		"fileSizeTypes": [
			"",
			"",
			"",
			"",
			"",
			"",
			"",
			"",
			""
		],
		"filter": "",
		"gt": "",
		"gte": "",
		"lt": "",
		"lte": "",
		"matchAll": "",
		"matchAny": "",
		"medium": "",
		"monthNames": [
			"",
			"",
			"",
			"",
			"",
			"",
			"",
			"",
			"",
			"",
			"",
			""
		],
		"monthNamesShort": [
			"",
			"",
			"",
			"",
			"",
			"",
			"",
			"",
			"",
			"",
			"",
			""
		],
		"nextDecade": "",
		"nextHour": "",
		"nextMinute": "",
		"nextMonth": "",
		"nextSecond": "",
		"nextYear": "",
		"noFileChosenMessage": "",
		"noFilter": "",
		"notContains": "",
		"notEquals": "",
		"now": "",
		"passwordPrompt": "",
		"pending": "",
		"pm": "",
		"prevDecade": "",
		"prevHour": "",
		"prevMinute": "",
		"prevMonth": "",
		"prevSecond": "",
		"prevYear": "",
		"reject": "",
		"removeRule": "",
		"searchMessage": "",
		"selectionMessage": "",
		"startsWith": "",
		"strong": "",
		"today": "",
		"upload": "",
		"weak": "",
		"weekHeader": ""
	},
	"de-AT": {
		"accept": "",
		"addRule": "",
		"am": "",
		"apply": "",
		"aria": {
			"cancelEdit": "",
			"close": "",
			"collapseLabel": "",
			"collapseRow": "",
			"editRow": "",
			"expandLabel": "",
			"expandRow": "",
			"falseLabel": "",
			"filterConstraint": "",
			"filterOperator": "",
			"firstPageLabel": "",
			"gridView": "",
			"hideFilterMenu": "",
			"jumpToPageDropdownLabel": "",
			"jumpToPageInputLabel": "",
			"lastPageLabel": "",
			"listLabel": "",
			"listView": "",
			"maximizeLabel": "",
			"minimizeLabel": "",
			"moveAllToSource": "",
			"moveAllToTarget": "",
			"moveBottom": "",
			"moveDown": "",
			"moveTop": "",
			"moveToSource": "",
			"moveToTarget": "",
			"moveUp": "",
			"navigation": "",
			"next": "",
			"nextPageLabel": "",
			"nullLabel": "",
			"otpLabel": "",
			"pageLabel": "",
			"passwordHide": "",
			"passwordShow": "",
			"previous": "",
			"prevPageLabel": "",
			"removeLabel": "",
			"rotateLeft": "",
			"rotateRight": "",
			"rowsPerPageLabel": "",
			"saveEdit": "",
			"scrollTop": "",
			"selectAll": "",
			"selectColor": "",
			"selectLabel": "",
			"selectRow": "",
			"showFilterMenu": "",
			"slide": "",
			"slideNumber": "",
			"star": "",
			"stars": "",
			"trueLabel": "",
			"unselectAll": "",
			"unselectLabel": "",
			"unselectRow": "",
			"zoomImage": "",
			"zoomIn": "",
			"zoomOut": ""
		},
		"cancel": "",
		"choose": "",
		"chooseDate": "",
		"chooseMonth": "",
		"chooseYear": "",
		"clear": "",
		"completed": "",
		"contains": "",
		"custom": "",
		"dateAfter": "",
		"dateBefore": "",
		"dateFormat": "",
		"dateIs": "",
		"dateIsNot": "",
		"dayNames": [
			"",
			"",
			"",
			"",
			"",
			"",
			""
		],
		"dayNamesMin": [
			"",
			"",
			"",
			"",
			"",
			"",
			""
		],
		"dayNamesShort": [
			"",
			"",
			"",
			"",
			"",
			"",
			""
		],
		"emptyFilterMessage": "",
		"emptyMessage": "",
		"emptySearchMessage": "",
		"emptySelectionMessage": "",
		"endsWith": "",
		"equals": "",
		"fileChosenMessage": "",
		"fileSizeTypes": [
			"",
			"",
			"",
			"",
			"",
			"",
			"",
			"",
			""
		],
		"filter": "",
		"gt": "",
		"gte": "",
		"lt": "",
		"lte": "",
		"matchAll": "",
		"matchAny": "",
		"medium": "",
		"monthNames": [
			"",
			"",
			"",
			"",
			"",
			"",
			"",
			"",
			"",
			"",
			"",
			""
		],
		"monthNamesShort": [
			"",
			"",
			"",
			"",
			"",
			"",
			"",
			"",
			"",
			"",
			"",
			""
		],
		"nextDecade": "",
		"nextHour": "",
		"nextMinute": "",
		"nextMonth": "",
		"nextSecond": "",
		"nextYear": "",
		"noFileChosenMessage": "",
		"noFilter": "",
		"notContains": "",
		"notEquals": "",
		"now": "",
		"passwordPrompt": "",
		"pending": "",
		"pm": "",
		"prevDecade": "",
		"prevHour": "",
		"prevMinute": "",
		"prevMonth": "",
		"prevSecond": "",
		"prevYear": "",
		"reject": "",
		"removeRule": "",
		"searchMessage": "",
		"selectionMessage": "",
		"startsWith": "",
		"strong": "",
		"today": "",
		"upload": "",
		"weak": "",
		"weekHeader": ""
	},
	"de-CH": {
		"accept": "",
		"addRule": "",
		"am": "",
		"apply": "",
		"aria": {
			"cancelEdit": "",
			"close": "",
			"collapseLabel": "",
			"collapseRow": "",
			"editRow": "",
			"expandLabel": "",
			"expandRow": "",
			"falseLabel": "",
			"filterConstraint": "",
			"filterOperator": "",
			"firstPageLabel": "",
			"gridView": "",
			"hideFilterMenu": "",
			"jumpToPageDropdownLabel": "",
			"jumpToPageInputLabel": "",
			"lastPageLabel": "",
			"listLabel": "",
			"listView": "",
			"maximizeLabel": "",
			"minimizeLabel": "",
			"moveAllToSource": "",
			"moveAllToTarget": "",
			"moveBottom": "",
			"moveDown": "",
			"moveTop": "",
			"moveToSource": "",
			"moveToTarget": "",
			"moveUp": "",
			"navigation": "",
			"next": "",
			"nextPageLabel": "",
			"nullLabel": "",
			"otpLabel": "",
			"pageLabel": "",
			"passwordHide": "",
			"passwordShow": "",
			"previous": "",
			"prevPageLabel": "",
			"removeLabel": "",
			"rotateLeft": "",
			"rotateRight": "",
			"rowsPerPageLabel": "",
			"saveEdit": "",
			"scrollTop": "",
			"selectAll": "",
			"selectColor": "",
			"selectLabel": "",
			"selectRow": "",
			"showFilterMenu": "",
			"slide": "",
			"slideNumber": "",
			"star": "",
			"stars": "",
			"trueLabel": "",
			"unselectAll": "",
			"unselectLabel": "",
			"unselectRow": "",
			"zoomImage": "",
			"zoomIn": "",
			"zoomOut": ""
		},
		"cancel": "",
		"choose": "",
		"chooseDate": "",
		"chooseMonth": "",
		"chooseYear": "",
		"clear": "",
		"completed": "",
		"contains": "",
		"custom": "",
		"dateAfter": "",
		"dateBefore": "",
		"dateFormat": "",
		"dateIs": "",
		"dateIsNot": "",
		"dayNames": [
			"",
			"",
			"",
			"",
			"",
			"",
			""
		],
		"dayNamesMin": [
			"",
			"",
			"",
			"",
			"",
			"",
			""
		],
		"dayNamesShort": [
			"",
			"",
			"",
			"",
			"",
			"",
			""
		],
		"emptyFilterMessage": "",
		"emptyMessage": "",
		"emptySearchMessage": "",
		"emptySelectionMessage": "",
		"endsWith": "",
		"equals": "",
		"fileChosenMessage": "",
		"fileSizeTypes": [
			"",
			"",
			"",
			"",
			"",
			"",
			"",
			"",
			""
		],
		"filter": "",
		"gt": "",
		"gte": "",
		"lt": "",
		"lte": "",
		"matchAll": "",
		"matchAny": "",
		"medium": "",
		"monthNames": [
			"",
			"",
			"",
			"",
			"",
			"",
			"",
			"",
			"",
			"",
			"",
			""
		],
		"monthNamesShort": [
			"",
			"",
			"",
			"",
			"",
			"",
			"",
			"",
			"",
			"",
			"",
			""
		],
		"nextDecade": "",
		"nextHour": "",
		"nextMinute": "",
		"nextMonth": "",
		"nextSecond": "",
		"nextYear": "",
		"noFileChosenMessage": "",
		"noFilter": "",
		"notContains": "",
		"notEquals": "",
		"now": "",
		"passwordPrompt": "",
		"pending": "",
		"pm": "",
		"prevDecade": "",
		"prevHour": "",
		"prevMinute": "",
		"prevMonth": "",
		"prevSecond": "",
		"prevYear": "",
		"reject": "",
		"removeRule": "",
		"searchMessage": "",
		"selectionMessage": "",
		"startsWith": "",
		"strong": "",
		"today": "",
		"upload": "",
		"weak": "",
		"weekHeader": ""
	},
	"el": {
		"accept": "",
		"addRule": "",
		"am": "",
		"apply": "",
		"aria": {
			"cancelEdit": "",
			"close": "",
			"collapseLabel": "",
			"collapseRow": "",
			"editRow": "",
			"expandLabel": "",
			"expandRow": "",
			"falseLabel": "",
			"filterConstraint": "",
			"filterOperator": "",
			"firstPageLabel": "",
			"gridView": "",
			"hideFilterMenu": "",
			"jumpToPageDropdownLabel": "",
			"jumpToPageInputLabel": "",
			"lastPageLabel": "",
			"listLabel": "",
			"listView": "",
			"maximizeLabel": "",
			"minimizeLabel": "",
			"moveAllToSource": "",
			"moveAllToTarget": "",
			"moveBottom": "",
			"moveDown": "",
			"moveTop": "",
			"moveToSource": "",
			"moveToTarget": "",
			"moveUp": "",
			"navigation": "",
			"next": "",
			"nextPageLabel": "",
			"nullLabel": "",
			"otpLabel": "",
			"pageLabel": "",
			"passwordHide": "",
			"passwordShow": "",
			"previous": "",
			"prevPageLabel": "",
			"removeLabel": "",
			"rotateLeft": "",
			"rotateRight": "",
			"rowsPerPageLabel": "",
			"saveEdit": "",
			"scrollTop": "",
			"selectAll": "",
			"selectColor": "",
			"selectLabel": "",
			"selectRow": "",
			"showFilterMenu": "",
			"slide": "",
			"slideNumber": "",
			"star": "",
			"stars": "",
			"trueLabel": "",
			"unselectAll": "",
			"unselectLabel": "",
			"unselectRow": "",
			"zoomImage": "",
			"zoomIn": "",
			"zoomOut": ""
		},
		"cancel": "",
		"choose": "",
		"chooseDate": "",
		"chooseMonth": "",
		"chooseYear": "",
		"clear": "",
		"completed": "",
		"contains": "",
		"custom": "",
		"dateAfter": "",
		"dateBefore": "",
		"dateFormat": "",
		"dateIs": "",
		"dateIsNot": "",
		"dayNames": [
			"",
			"",
			"",
			"",
			"",
			"",
			""
		],
		"dayNamesMin": [
			"",
			"",
			"",
			"",
			"",
			"",
			""
		],
		"dayNamesShort": [
			"",
			"",
			"",
			"",
			"",
			"",
			""
		],
		"emptyFilterMessage": "",
		"emptyMessage": "",
		"emptySearchMessage": "",
		"emptySelectionMessage": "",
		"endsWith": "",
		"equals": "",
		"fileChosenMessage": "",
		"fileSizeTypes": [
			"",
			"",
			"",
			"",
			"",
			"",
			"",
			"",
			""
		],
		"filter": "",
		"gt": "",
		"gte": "",
		"lt": "",
		"lte": "",
		"matchAll": "",
		"matchAny": "",
		"medium": "",
		"monthNames": [
			"",
			"",
			"",
			"",
			"",
			"",
			"",
			"",
			"",
			"",
			"",
			""
		],
		"monthNamesShort": [
			"",
			"",
			"",
			"",
			"",
			"",
			"",
			"",
			"",
			"",
			"",
			""
		],
		"nextDecade": "",
		"nextHour": "",
		"nextMinute": "",
		"nextMonth": "",
		"nextSecond": "",
		"nextYear": "",
		"noFileChosenMessage": "",
		"noFilter": "",
		"notContains": "",
		"notEquals": "",
		"now": "",
		"passwordPrompt": "",
		"pending": "",
		"pm": "",
		"prevDecade": "",
		"prevHour": "",
		"prevMinute": "",
		"prevMonth": "",
		"prevSecond": "",
		"prevYear": "",
		"reject": "",
		"removeRule": "",
		"searchMessage": "",
		"selectionMessage": "",
		"startsWith": "",
		"strong": "",
		"today": "",
		"upload": "",
		"weak": "",
		"weekHeader": ""
	},
	"en": {
		"accept": "",
		"addRule": "",
		"am": "",
		"apply": "",
		"aria": {
			"cancelEdit": "",
			"close": "",
			"collapseLabel": "",
			"collapseRow": "",
			"editRow": "",
			"expandLabel": "",
			"expandRow": "",
			"falseLabel": "",
			"filterConstraint": "",
			"filterOperator": "",
			"firstPageLabel": "",
			"gridView": "",
			"hideFilterMenu": "",
			"jumpToPageDropdownLabel": "",
			"jumpToPageInputLabel": "",
			"lastPageLabel": "",
			"listLabel": "",
			"listView": "",
			"maximizeLabel": "",
			"minimizeLabel": "",
			"moveAllToSource": "",
			"moveAllToTarget": "",
			"moveBottom": "",
			"moveDown": "",
			"moveTop": "",
			"moveToSource": "",
			"moveToTarget": "",
			"moveUp": "",
			"navigation": "",
			"next": "",
			"nextPageLabel": "",
			"nullLabel": "",
			"otpLabel": "",
			"pageLabel": "",
			"passwordHide": "",
			"passwordShow": "",
			"previous": "",
			"prevPageLabel": "",
			"removeLabel": "",
			"rotateLeft": "",
			"rotateRight": "",
			"rowsPerPageLabel": "",
			"saveEdit": "",
			"scrollTop": "",
			"selectAll": "",
			"selectColor": "",
			"selectLabel": "",
			"selectRow": "",
			"showFilterMenu": "",
			"slide": "",
			"slideNumber": "",
			"star": "",
			"stars": "",
			"trueLabel": "",
			"unselectAll": "",
			"unselectLabel": "",
			"unselectRow": "",
			"zoomImage": "",
			"zoomIn": "",
			"zoomOut": ""
		},
		"cancel": "",
		"choose": "",
		"chooseDate": "",
		"chooseMonth": "",
		"chooseYear": "",
		"clear": "",
		"completed": "",
		"contains": "",
		"custom": "",
		"dateAfter": "",
		"dateBefore": "",
		"dateFormat": "",
		"dateIs": "",
		"dateIsNot": "",
		"dayNames": [
			"",
			"",
			"",
			"",
			"",
			"",
			""
		],
		"dayNamesMin": [
			"",
			"",
			"",
			"",
			"",
			"",
			""
		],
		"dayNamesShort": [
			"",
			"",
			"",
			"",
			"",
			"",
			""
		],
		"emptyFilterMessage": "",
		"emptyMessage": "",
		"emptySearchMessage": "",
		"emptySelectionMessage": "",
		"endsWith": "",
		"equals": "",
		"fileChosenMessage": "",
		"fileSizeTypes": [
			"",
			"",
			"",
			"",
			"",
			"",
			"",
			"",
			""
		],
		"filter": "",
		"gt": "",
		"gte": "",
		"lt": "",
		"lte": "",
		"matchAll": "",
		"matchAny": "",
		"medium": "",
		"monthNames": [
			"",
			"",
			"",
			"",
			"",
			"",
			"",
			"",
			"",
			"",
			"",
			""
		],
		"monthNamesShort": [
			"",
			"",
			"",
			"",
			"",
			"",
			"",
			"",
			"",
			"",
			"",
			""
		],
		"nextDecade": "",
		"nextHour": "",
		"nextMinute": "",
		"nextMonth": "",
		"nextSecond": "",
		"nextYear": "",
		"noFileChosenMessage": "",
		"noFilter": "",
		"notContains": "",
		"notEquals": "",
		"now": "",
		"passwordPrompt": "",
		"pending": "",
		"pm": "",
		"prevDecade": "",
		"prevHour": "",
		"prevMinute": "",
		"prevMonth": "",
		"prevSecond": "",
		"prevYear": "",
		"reject": "",
		"removeRule": "",
		"searchMessage": "",
		"selectionMessage": "",
		"startsWith": "",
		"strong": "",
		"today": "",
		"upload": "",
		"weak": "",
		"weekHeader": ""
	},
	"en-AU": {
		"accept": "",
		"addRule": "",
		"am": "",
		"apply": "",
		"aria": {
			"cancelEdit": "",
			"close": "",
			"collapseLabel": "",
			"collapseRow": "",
			"editRow": "",
			"expandLabel": "",
			"expandRow": "",
			"falseLabel": "",
			"filterConstraint": "",
			"filterOperator": "",
			"firstPageLabel": "",
			"gridView": "",
			"hideFilterMenu": "",
			"jumpToPageDropdownLabel": "",
			"jumpToPageInputLabel": "",
			"lastPageLabel": "",
			"listLabel": "",
			"listView": "",
			"maximizeLabel": "",
			"minimizeLabel": "",
			"moveAllToSource": "",
			"moveAllToTarget": "",
			"moveBottom": "",
			"moveDown": "",
			"moveTop": "",
			"moveToSource": "",
			"moveToTarget": "",
			"moveUp": "",
			"navigation": "",
			"next": "",
			"nextPageLabel": "",
			"nullLabel": "",
			"otpLabel": "",
			"pageLabel": "",
			"passwordHide": "",
			"passwordShow": "",
			"previous": "",
			"prevPageLabel": "",
			"removeLabel": "",
			"rotateLeft": "",
			"rotateRight": "",
			"rowsPerPageLabel": "",
			"saveEdit": "",
			"scrollTop": "",
			"selectAll": "",
			"selectColor": "",
			"selectLabel": "",
			"selectRow": "",
			"showFilterMenu": "",
			"slide": "",
			"slideNumber": "",
			"star": "",
			"stars": "",
			"trueLabel": "",
			"unselectAll": "",
			"unselectLabel": "",
			"unselectRow": "",
			"zoomImage": "",
			"zoomIn": "",
			"zoomOut": ""
		},
		"cancel": "",
		"choose": "",
		"chooseDate": "",
		"chooseMonth": "",
		"chooseYear": "",
		"clear": "",
		"completed": "",
		"contains": "",
		"custom": "",
		"dateAfter": "",
		"dateBefore": "",
		"dateFormat": "",
		"dateIs": "",
		"dateIsNot": "",
		"dayNames": [
			"",
			"",
			"",
			"",
			"",
			"",
			""
		],
		"dayNamesMin": [
			"",
			"",
			"",
			"",
			"",
			"",
			""
		],
		"dayNamesShort": [
			"",
			"",
			"",
			"",
			"",
			"",
			""
		],
		"emptyFilterMessage": "",
		"emptyMessage": "",
		"emptySearchMessage": "",
		"emptySelectionMessage": "",
		"endsWith": "",
		"equals": "",
		"fileChosenMessage": "",
		"fileSizeTypes": [
			"",
			"",
			"",
			"",
			"",
			"",
			"",
			"",
			""
		],
		"filter": "",
		"gt": "",
		"gte": "",
		"lt": "",
		"lte": "",
		"matchAll": "",
		"matchAny": "",
		"medium": "",
		"monthNames": [
			"",
			"",
			"",
			"",
			"",
			"",
			"",
			"",
			"",
			"",
			"",
			""
		],
		"monthNamesShort": [
			"",
			"",
			"",
			"",
			"",
			"",
			"",
			"",
			"",
			"",
			"",
			""
		],
		"nextDecade": "",
		"nextHour": "",
		"nextMinute": "",
		"nextMonth": "",
		"nextSecond": "",
		"nextYear": "",
		"noFileChosenMessage": "",
		"noFilter": "",
		"notContains": "",
		"notEquals": "",
		"now": "",
		"passwordPrompt": "",
		"pending": "",
		"pm": "",
		"prevDecade": "",
		"prevHour": "",
		"prevMinute": "",
		"prevMonth": "",
		"prevSecond": "",
		"prevYear": "",
		"reject": "",
		"removeRule": "",
		"searchMessage": "",
		"selectionMessage": "",
		"startsWith": "",
		"strong": "",
		"today": "",
		"upload": "",
		"weak": "",
		"weekHeader": ""
	},
	"en-GB": {
		"accept": "",
		"addRule": "",
		"am": "",
		"apply": "",
		"aria": {
			"cancelEdit": "",
			"close": "",
			"collapseLabel": "",
			"collapseRow": "",
			"editRow": "",
			"expandLabel": "",
			"expandRow": "",
			"falseLabel": "",
			"filterConstraint": "",
			"filterOperator": "",
			"firstPageLabel": "",
			"gridView": "",
			"hideFilterMenu": "",
			"jumpToPageDropdownLabel": "",
			"jumpToPageInputLabel": "",
			"lastPageLabel": "",
			"listLabel": "",
			"listView": "",
			"maximizeLabel": "",
			"minimizeLabel": "",
			"moveAllToSource": "",
			"moveAllToTarget": "",
			"moveBottom": "",
			"moveDown": "",
			"moveTop": "",
			"moveToSource": "",
			"moveToTarget": "",
			"moveUp": "",
			"navigation": "",
			"next": "",
			"nextPageLabel": "",
			"nullLabel": "",
			"otpLabel": "",
			"pageLabel": "",
			"passwordHide": "",
			"passwordShow": "",
			"previous": "",
			"prevPageLabel": "",
			"removeLabel": "",
			"rotateLeft": "",
			"rotateRight": "",
			"rowsPerPageLabel": "",
			"saveEdit": "",
			"scrollTop": "",
			"selectAll": "",
			"selectColor": "",
			"selectLabel": "",
			"selectRow": "",
			"showFilterMenu": "",
			"slide": "",
			"slideNumber": "",
			"star": "",
			"stars": "",
			"trueLabel": "",
			"unselectAll": "",
			"unselectLabel": "",
			"unselectRow": "",
			"zoomImage": "",
			"zoomIn": "",
			"zoomOut": ""
		},
		"cancel": "",
		"choose": "",
		"chooseDate": "",
		"chooseMonth": "",
		"chooseYear": "",
		"clear": "",
		"completed": "",
		"contains": "",
		"custom": "",
		"dateAfter": "",
		"dateBefore": "",
		"dateFormat": "",
		"dateIs": "",
		"dateIsNot": "",
		"dayNames": [
			"",
			"",
			"",
			"",
			"",
			"",
			""
		],
		"dayNamesMin": [
			"",
			"",
			"",
			"",
			"",
			"",
			""
		],
		"dayNamesShort": [
			"",
			"",
			"",
			"",
			"",
			"",
			""
		],
		"emptyFilterMessage": "",
		"emptyMessage": "",
		"emptySearchMessage": "",
		"emptySelectionMessage": "",
		"endsWith": "",
		"equals": "",
		"fileChosenMessage": "",
		"fileSizeTypes": [
			"",
			"",
			"",
			"",
			"",
			"",
			"",
			"",
			""
		],
		"filter": "",
		"gt": "",
		"gte": "",
		"lt": "",
		"lte": "",
		"matchAll": "",
		"matchAny": "",
		"medium": "",
		"monthNames": [
			"",
			"",
			"",
			"",
			"",
			"",
			"",
			"",
			"",
			"",
			"",
			""
		],
		"monthNamesShort": [
			"",
			"",
			"",
			"",
			"",
			"",
			"",
			"",
			"",
			"",
			"",
			""
		],
		"nextDecade": "",
		"nextHour": "",
		"nextMinute": "",
		"nextMonth": "",
		"nextSecond": "",
		"nextYear": "",
		"noFileChosenMessage": "",
		"noFilter": "",
		"notContains": "",
		"notEquals": "",
		"now": "",
		"passwordPrompt": "",
		"pending": "",
		"pm": "",
		"prevDecade": "",
		"prevHour": "",
		"prevMinute": "",
		"prevMonth": "",
		"prevSecond": "",
		"prevYear": "",
		"reject": "",
		"removeRule": "",
		"searchMessage": "",
		"selectionMessage": "",
		"startsWith": "",
		"strong": "",
		"today": "",
		"upload": "",
		"weak": "",
		"weekHeader": ""
	},
	"es": {
		"accept": "",
		"addRule": "",
		"am": "",
		"apply": "",
		"aria": {
			"cancelEdit": "",
			"close": "",
			"collapseLabel": "",
			"collapseRow": "",
			"editRow": "",
			"expandLabel": "",
			"expandRow": "",
			"falseLabel": "",
			"filterConstraint": "",
			"filterOperator": "",
			"firstPageLabel": "",
			"gridView": "",
			"hideFilterMenu": "",
			"jumpToPageDropdownLabel": "",
			"jumpToPageInputLabel": "",
			"lastPageLabel": "",
			"listLabel": "",
			"listView": "",
			"maximizeLabel": "",
			"minimizeLabel": "",
			"moveAllToSource": "",
			"moveAllToTarget": "",
			"moveBottom": "",
			"moveDown": "",
			"moveTop": "",
			"moveToSource": "",
			"moveToTarget": "",
			"moveUp": "",
			"navigation": "",
			"next": "",
			"nextPageLabel": "",
			"nullLabel": "",
			"otpLabel": "",
			"pageLabel": "",
			"passwordHide": "",
			"passwordShow": "",
			"previous": "",
			"prevPageLabel": "",
			"removeLabel": "",
			"rotateLeft": "",
			"rotateRight": "",
			"rowsPerPageLabel": "",
			"saveEdit": "",
			"scrollTop": "",
			"selectAll": "",
			"selectColor": "",
			"selectLabel": "",
			"selectRow": "",
			"showFilterMenu": "",
			"slide": "",
			"slideNumber": "",
			"star": "",
			"stars": "",
			"trueLabel": "",
			"unselectAll": "",
			"unselectLabel": "",
			"unselectRow": "",
			"zoomImage": "",
			"zoomIn": "",
			"zoomOut": ""
		},
		"cancel": "",
		"choose": "",
		"chooseDate": "",
		"chooseMonth": "",
		"chooseYear": "",
		"clear": "",
		"completed": "",
		"contains": "",
		"custom": "",
		"dateAfter": "",
		"dateBefore": "",
		"dateFormat": "",
		"dateIs": "",
		"dateIsNot": "",
		"dayNames": [
			"",
			"",
			"",
			"",
			"",
			"",
			""
		],
		"dayNamesMin": [
			"",
			"",
			"",
			"",
			"",
			"",
			""
		],
		"dayNamesShort": [
			"",
			"",
			"",
			"",
			"",
			"",
			""
		],
		"emptyFilterMessage": "",
		"emptyMessage": "",
		"emptySearchMessage": "",
		"emptySelectionMessage": "",
		"endsWith": "",
		"equals": "",
		"fileChosenMessage": "",
		"fileSizeTypes": [
			"",
			"",
			"",
			"",
			"",
			"",
			"",
			"",
			""
		],
		"filter": "",
		"gt": "",
		"gte": "",
		"lt": "",
		"lte": "",
		"matchAll": "",
		"matchAny": "",
		"medium": "",
		"monthNames": [
			"",
			"",
			"",
			"",
			"",
			"",
			"",
			"",
			"",
			"",
			"",
			""
		],
		"monthNamesShort": [
			"",
			"",
			"",
			"",
			"",
			"",
			"",
			"",
			"",
			"",
			"",
			""
		],
		"nextDecade": "",
		"nextHour": "",
		"nextMinute": "",
		"nextMonth": "",
		"nextSecond": "",
		"nextYear": "",
		"noFileChosenMessage": "",
		"noFilter": "",
		"notContains": "",
		"notEquals": "",
		"now": "",
		"passwordPrompt": "",
		"pending": "",
		"pm": "",
		"prevDecade": "",
		"prevHour": "",
		"prevMinute": "",
		"prevMonth": "",
		"prevSecond": "",
		"prevYear": "",
		"reject": "",
		"removeRule": "",
		"searchMessage": "",
		"selectionMessage": "",
		"startsWith": "",
		"strong": "",
		"today": "",
		"upload": "",
		"weak": "",
		"weekHeader": ""
	},
	"et": {
		"accept": "Jah",
		"addRule": "Lisa reegel",
		"am": "AM",
		"apply": "Rakenda",
		"aria": {
			"cancelEdit": "Tühista redigeerimine",
			"close": "Sulge",
			"collapseLabel": "Suru kokku",
			"collapseRow": "Rida kokku surutud",
			"editRow": "Redigeeri rida",
			"expandLabel": "Laienda",
			"expandRow": "Rida laiendatud",
			"falseLabel": "Vale",
			"filterConstraint": "Filtri piirang",
			"filterOperator": "Filtri operaator",
			"firstPageLabel": "Esimene lehekülg",
			"gridView": "Ruudustikuvaade",
			"hideFilterMenu": "Peida filtrimenüü",
			"jumpToPageDropdownLabel": "Hüppa lehe rippmenüüsse",
			"jumpToPageInputLabel": "Hüppa lehe sisendisse",
			"lastPageLabel": "Viimane lehekülg",
			"listLabel": "Valikute loend",
			"listView": "Loendivaade",
			"maximizeLabel": "Maksimeeri",
			"minimizeLabel": "Minimeeri",
			"moveAllToSource": "Liiguta kõik allikasse",
			"moveAllToTarget": "Liiguta kõik sihtkohta",
			"moveBottom": "Liiguta alla",
			"moveDown": "Liiguta allapoole",
			"moveTop": "Liiguta üles",
			"moveToSource": "Liiguta allikasse",
			"moveToTarget": "Liiguta sihtkohta",
			"moveUp": "Liiguta ülespoole",
			"navigation": "Navigatsioon",
			"next": "Järgmine",
			"nextPageLabel": "Järgmine lehekülg",
			"nullLabel": "Pole valitud",
			"otpLabel": "Palun sisestage ühekordse parooli märk {0}",
			"pageLabel": "Lehekülg {page}",
			"passwordHide": "Peida parool",
			"passwordShow": "Näita parooli",
			"previous": "Eelmine",
			"prevPageLabel": "Eelmine lehekülg",
			"removeLabel": "Eemalda",
			"rotateLeft": "Pööra vasakule",
			"rotateRight": "Pööra paremale",
			"rowsPerPageLabel": "Ridu leheküljel",
			"saveEdit": "Salvesta redigeerimine",
			"scrollTop": "Kerige üles",
			"selectAll": "Kõik elemendid valitud",
			"selectColor": "Valige värv",
			"selectLabel": "Vali",
			"selectRow": "Rida valitud",
			"showFilterMenu": "Näita filtrimenüüd",
			"slide": "Slaid",
			"slideNumber": "{slideNumber}",
			"star": "1 täht",
			"stars": "{star} tähte",
			"trueLabel": "Tõene",
			"unselectAll": "Kõik elemendid tühistatud",
			"unselectLabel": "Tühista valik",
			"unselectRow": "Rida tühistatud",
			"zoomImage": "Suumi pilti",
			"zoomIn": "Suumi sisse",
			"zoomOut": "Suumi välja"
		},
		"cancel": "Tühista",
		"choose": "Vali",
		"chooseDate": "Vali kuupäev",
		"chooseMonth": "Vali kuu",
		"chooseYear": "Vali aasta",
		"clear": "Tühjenda",
		"completed": "Lõpetatud",
		"contains": "Sisaldab",
		"custom": "Kohandatud",
		"dateAfter": "Kuupäev on pärast",
		"dateBefore": "Kuupäev on enne",
		"dateFormat": "dd.mm.yy",
		"dateIs": "Kuupäev on",
		"dateIsNot": "Kuupäev ei ole",
		"dayNames": [
			"Pühapäev",
			"Esmaspäev",
			"Teisipäev",
			"Kolmapäev",
			"Neljapäev",
			"Reede",
			"Laupäev"
		],
		"dayNamesMin": [
			"P",
			"E",
			"T",
			"K",
			"N",
			"R",
			"L"
		],
		"dayNamesShort": [
			"Püh",
			"Esm",
			"Teis",
			"Kol",
			"Nelj",
			"Ree",
			"Lau"
		],
		"emptyFilterMessage": "Tulemusi ei leitud",
		"emptyMessage": "Valikuid pole saadaval",
		"emptySearchMessage": "Tulemusi ei leitud",
		"emptySelectionMessage": "Ükski element pole valitud",
		"endsWith": "Lõpeb",
		"equals": "Võrdub",
		"fileChosenMessage": "{0} faili",
		"fileSizeTypes": [
			"B",
			"KB",
			"MB",
			"GB",
			"TB",
			"PB",
			"EB",
			"ZB",
			"YB"
		],
		"filter": "Filtreeri",
		"gt": "Suurem kui",
		"gte": "Suurem või võrdne",
		"lt": "Väiksem kui",
		"lte": "Väiksem või võrdne",
		"matchAll": "Sobib kõik",
		"matchAny": "Sobita mõni",
		"medium": "Keskmine",
		"monthNames": [
			"Jaanuar",
			"Veebruar",
			"Märts",
			"Aprill",
			"Mai",
			"Juuni",
			"Juuli",
			"August",
			"September",
			"Oktoober",
			"November",
			"Detsember"
		],
		"monthNamesShort": [
			"Jaan",
			"Veeb",
			"Mär",
			"Apr",
			"Mai",
			"Juun",
			"Juul",
			"Aug",
			"Sept",
			"Okt",
			"Nov",
			"Dets"
		],
		"nextDecade": "Järgmine aastakümme",
		"nextHour": "Järgmine tund",
		"nextMinute": "Järgmine minut",
		"nextMonth": "Järgmine kuu",
		"nextSecond": "Järgmine sekund",
		"nextYear": "Järgmine aasta",
		"noFileChosenMessage": "Faili pole valitud",
		"noFilter": "Ilma filtrita",
		"notContains": "Ei sisalda",
		"notEquals": "Ei võrdu",
		"now": "Praegu",
		"passwordPrompt": "Sisestage parool",
		"pending": "Ootel",
		"pm": "PM",
		"prevDecade": "Eelmine aastakümme",
		"prevHour": "Eelmine tund",
		"prevMinute": "Eelmine minut",
		"prevMonth": "Eelmine kuu",
		"prevSecond": "Eelmine sekund",
		"prevYear": "Eelmine aasta",
		"reject": "Ei",
		"removeRule": "Eemalda reegel",
		"searchMessage": "{0} tulemust on saadaval",
		"selectionMessage": "{0} elementi valitud",
		"startsWith": "Algab",
		"strong": "Tugev",
		"today": "Täna",
		"upload": "Laadi üles",
		"weak": "Nõrk",
		"weekHeader": "Näd"
	},
	"fa": {
		"accept": "",
		"addRule": "",
		"am": "",
		"apply": "",
		"aria": {
			"cancelEdit": "",
			"close": "",
			"collapseLabel": "",
			"collapseRow": "",
			"editRow": "",
			"expandLabel": "",
			"expandRow": "",
			"falseLabel": "",
			"filterConstraint": "",
			"filterOperator": "",
			"firstPageLabel": "",
			"gridView": "",
			"hideFilterMenu": "",
			"jumpToPageDropdownLabel": "",
			"jumpToPageInputLabel": "",
			"lastPageLabel": "",
			"listLabel": "",
			"listView": "",
			"maximizeLabel": "",
			"minimizeLabel": "",
			"moveAllToSource": "",
			"moveAllToTarget": "",
			"moveBottom": "",
			"moveDown": "",
			"moveTop": "",
			"moveToSource": "",
			"moveToTarget": "",
			"moveUp": "",
			"navigation": "",
			"next": "",
			"nextPageLabel": "",
			"nullLabel": "",
			"otpLabel": "",
			"pageLabel": "",
			"passwordHide": "",
			"passwordShow": "",
			"previous": "",
			"prevPageLabel": "",
			"removeLabel": "",
			"rotateLeft": "",
			"rotateRight": "",
			"rowsPerPageLabel": "",
			"saveEdit": "",
			"scrollTop": "",
			"selectAll": "",
			"selectColor": "",
			"selectLabel": "",
			"selectRow": "",
			"showFilterMenu": "",
			"slide": "",
			"slideNumber": "",
			"star": "",
			"stars": "",
			"trueLabel": "",
			"unselectAll": "",
			"unselectLabel": "",
			"unselectRow": "",
			"zoomImage": "",
			"zoomIn": "",
			"zoomOut": ""
		},
		"cancel": "",
		"choose": "",
		"chooseDate": "",
		"chooseMonth": "",
		"chooseYear": "",
		"clear": "",
		"completed": "",
		"contains": "",
		"custom": "",
		"dateAfter": "",
		"dateBefore": "",
		"dateFormat": "",
		"dateIs": "",
		"dateIsNot": "",
		"dayNames": [
			"",
			"",
			"",
			"",
			"",
			"",
			""
		],
		"dayNamesMin": [
			"",
			"",
			"",
			"",
			"",
			"",
			""
		],
		"dayNamesShort": [
			"",
			"",
			"",
			"",
			"",
			"",
			""
		],
		"emptyFilterMessage": "",
		"emptyMessage": "",
		"emptySearchMessage": "",
		"emptySelectionMessage": "",
		"endsWith": "",
		"equals": "",
		"fileChosenMessage": "",
		"fileSizeTypes": [
			"",
			"",
			"",
			"",
			"",
			"",
			"",
			"",
			""
		],
		"filter": "",
		"gt": "",
		"gte": "",
		"lt": "",
		"lte": "",
		"matchAll": "",
		"matchAny": "",
		"medium": "",
		"monthNames": [
			"",
			"",
			"",
			"",
			"",
			"",
			"",
			"",
			"",
			"",
			"",
			""
		],
		"monthNamesShort": [
			"",
			"",
			"",
			"",
			"",
			"",
			"",
			"",
			"",
			"",
			"",
			""
		],
		"nextDecade": "",
		"nextHour": "",
		"nextMinute": "",
		"nextMonth": "",
		"nextSecond": "",
		"nextYear": "",
		"noFileChosenMessage": "",
		"noFilter": "",
		"notContains": "",
		"notEquals": "",
		"now": "",
		"passwordPrompt": "",
		"pending": "",
		"pm": "",
		"prevDecade": "",
		"prevHour": "",
		"prevMinute": "",
		"prevMonth": "",
		"prevSecond": "",
		"prevYear": "",
		"reject": "",
		"removeRule": "",
		"searchMessage": "",
		"selectionMessage": "",
		"startsWith": "",
		"strong": "",
		"today": "",
		"upload": "",
		"weak": "",
		"weekHeader": ""
	},
	"fi": {
		"accept": "",
		"addRule": "",
		"am": "",
		"apply": "",
		"aria": {
			"cancelEdit": "",
			"close": "",
			"collapseLabel": "",
			"collapseRow": "",
			"editRow": "",
			"expandLabel": "",
			"expandRow": "",
			"falseLabel": "",
			"filterConstraint": "",
			"filterOperator": "",
			"firstPageLabel": "",
			"gridView": "",
			"hideFilterMenu": "",
			"jumpToPageDropdownLabel": "",
			"jumpToPageInputLabel": "",
			"lastPageLabel": "",
			"listLabel": "",
			"listView": "",
			"maximizeLabel": "",
			"minimizeLabel": "",
			"moveAllToSource": "",
			"moveAllToTarget": "",
			"moveBottom": "",
			"moveDown": "",
			"moveTop": "",
			"moveToSource": "",
			"moveToTarget": "",
			"moveUp": "",
			"navigation": "",
			"next": "",
			"nextPageLabel": "",
			"nullLabel": "",
			"otpLabel": "",
			"pageLabel": "",
			"passwordHide": "",
			"passwordShow": "",
			"previous": "",
			"prevPageLabel": "",
			"removeLabel": "",
			"rotateLeft": "",
			"rotateRight": "",
			"rowsPerPageLabel": "",
			"saveEdit": "",
			"scrollTop": "",
			"selectAll": "",
			"selectColor": "",
			"selectLabel": "",
			"selectRow": "",
			"showFilterMenu": "",
			"slide": "",
			"slideNumber": "",
			"star": "",
			"stars": "",
			"trueLabel": "",
			"unselectAll": "",
			"unselectLabel": "",
			"unselectRow": "",
			"zoomImage": "",
			"zoomIn": "",
			"zoomOut": ""
		},
		"cancel": "",
		"choose": "",
		"chooseDate": "",
		"chooseMonth": "",
		"chooseYear": "",
		"clear": "",
		"completed": "",
		"contains": "",
		"custom": "",
		"dateAfter": "",
		"dateBefore": "",
		"dateFormat": "",
		"dateIs": "",
		"dateIsNot": "",
		"dayNames": [
			"",
			"",
			"",
			"",
			"",
			"",
			""
		],
		"dayNamesMin": [
			"",
			"",
			"",
			"",
			"",
			"",
			""
		],
		"dayNamesShort": [
			"",
			"",
			"",
			"",
			"",
			"",
			""
		],
		"emptyFilterMessage": "",
		"emptyMessage": "",
		"emptySearchMessage": "",
		"emptySelectionMessage": "",
		"endsWith": "",
		"equals": "",
		"fileChosenMessage": "",
		"fileSizeTypes": [
			"",
			"",
			"",
			"",
			"",
			"",
			"",
			"",
			""
		],
		"filter": "",
		"gt": "",
		"gte": "",
		"lt": "",
		"lte": "",
		"matchAll": "",
		"matchAny": "",
		"medium": "",
		"monthNames": [
			"",
			"",
			"",
			"",
			"",
			"",
			"",
			"",
			"",
			"",
			"",
			""
		],
		"monthNamesShort": [
			"",
			"",
			"",
			"",
			"",
			"",
			"",
			"",
			"",
			"",
			"",
			""
		],
		"nextDecade": "",
		"nextHour": "",
		"nextMinute": "",
		"nextMonth": "",
		"nextSecond": "",
		"nextYear": "",
		"noFileChosenMessage": "",
		"noFilter": "",
		"notContains": "",
		"notEquals": "",
		"now": "",
		"passwordPrompt": "",
		"pending": "",
		"pm": "",
		"prevDecade": "",
		"prevHour": "",
		"prevMinute": "",
		"prevMonth": "",
		"prevSecond": "",
		"prevYear": "",
		"reject": "",
		"removeRule": "",
		"searchMessage": "",
		"selectionMessage": "",
		"startsWith": "",
		"strong": "",
		"today": "",
		"upload": "",
		"weak": "",
		"weekHeader": ""
	},
	"ur": {
		"accept": "",
		"addRule": "",
		"am": "",
		"apply": "",
		"aria": {
			"cancelEdit": "",
			"close": "",
			"collapseLabel": "",
			"collapseRow": "",
			"editRow": "",
			"expandLabel": "",
			"expandRow": "",
			"falseLabel": "",
			"filterConstraint": "",
			"filterOperator": "",
			"firstPageLabel": "",
			"gridView": "",
			"hideFilterMenu": "",
			"jumpToPageDropdownLabel": "",
			"jumpToPageInputLabel": "",
			"lastPageLabel": "",
			"listLabel": "",
			"listView": "",
			"maximizeLabel": "",
			"minimizeLabel": "",
			"moveAllToSource": "",
			"moveAllToTarget": "",
			"moveBottom": "",
			"moveDown": "",
			"moveTop": "",
			"moveToSource": "",
			"moveToTarget": "",
			"moveUp": "",
			"navigation": "",
			"next": "",
			"nextPageLabel": "",
			"nullLabel": "",
			"otpLabel": "",
			"pageLabel": "",
			"passwordHide": "",
			"passwordShow": "",
			"previous": "",
			"prevPageLabel": "",
			"removeLabel": "",
			"rotateLeft": "",
			"rotateRight": "",
			"rowsPerPageLabel": "",
			"saveEdit": "",
			"scrollTop": "",
			"selectAll": "",
			"selectColor": "",
			"selectLabel": "",
			"selectRow": "",
			"showFilterMenu": "",
			"slide": "",
			"slideNumber": "",
			"star": "",
			"stars": "",
			"trueLabel": "",
			"unselectAll": "",
			"unselectLabel": "",
			"unselectRow": "",
			"zoomImage": "",
			"zoomIn": "",
			"zoomOut": ""
		},
		"cancel": "",
		"choose": "",
		"chooseDate": "",
		"chooseMonth": "",
		"chooseYear": "",
		"clear": "",
		"completed": "",
		"contains": "",
		"custom": "",
		"dateAfter": "",
		"dateBefore": "",
		"dateFormat": "",
		"dateIs": "",
		"dateIsNot": "",
		"dayNames": [
			"",
			"",
			"",
			"",
			"",
			"",
			""
		],
		"dayNamesMin": [
			"",
			"",
			"",
			"",
			"",
			"",
			""
		],
		"dayNamesShort": [
			"",
			"",
			"",
			"",
			"",
			"",
			""
		],
		"emptyFilterMessage": "",
		"emptyMessage": "",
		"emptySearchMessage": "",
		"emptySelectionMessage": "",
		"endsWith": "",
		"equals": "",
		"fileChosenMessage": "",
		"fileSizeTypes": [
			"",
			"",
			"",
			"",
			"",
			"",
			"",
			"",
			""
		],
		"filter": "",
		"gt": "",
		"gte": "",
		"lt": "",
		"lte": "",
		"matchAll": "",
		"matchAny": "",
		"medium": "",
		"monthNames": [
			"",
			"",
			"",
			"",
			"",
			"",
			"",
			"",
			"",
			"",
			"",
			""
		],
		"monthNamesShort": [
			"",
			"",
			"",
			"",
			"",
			"",
			"",
			"",
			"",
			"",
			"",
			""
		],
		"nextDecade": "",
		"nextHour": "",
		"nextMinute": "",
		"nextMonth": "",
		"nextSecond": "",
		"nextYear": "",
		"noFileChosenMessage": "",
		"noFilter": "",
		"notContains": "",
		"notEquals": "",
		"now": "",
		"passwordPrompt": "",
		"pending": "",
		"pm": "",
		"prevDecade": "",
		"prevHour": "",
		"prevMinute": "",
		"prevMonth": "",
		"prevSecond": "",
		"prevYear": "",
		"reject": "",
		"removeRule": "",
		"searchMessage": "",
		"selectionMessage": "",
		"startsWith": "",
		"strong": "",
		"today": "",
		"upload": "",
		"weak": "",
		"weekHeader": ""
	}
}
